pyglome/__init__.py
pyglome/glome.py
pyglome-0.0.2.dist-info/METADATA
pyglome-0.0.2.dist-info/WHEEL
pyglome-0.0.2.dist-info/top_level.txt
pyglome-0.0.2.dist-info/RECORD
