Metadata-Version: 2.1
Name: pyglome
Version: 0.0.2
Summary: A Python implementation of GLOME protocol
Home-page: https://github.com/google/glome
Author: Google LLC
License: UNKNOWN
Platform: UNKNOWN
Classifier: Programming Language :: Python :: 3
Classifier: License :: OSI Approved :: Apache Software License
Requires-Python: >=3.6
Requires-Dist: cryptography
